gopca/__init__.py
gopca/config.py
gopca/gopca.py
gopca/params.py
gopca/run.py
gopca/signature.py
gopca/signature_matrix.py
gopca/util.py
gopca/cli/__init__.py
gopca/cli/arguments.py
gopca/cli/combine_signatures.py
gopca/cli/convert_to_matlab.py
gopca/cli/extract_go_gene_sets.py
gopca/cli/extract_signature_matrix.py
gopca/cli/extract_signatures.py
gopca/cli/extract_signatures_excel.py
gopca/cli/filter_signatures.py
gopca/cli/go_pca.py
gopca/cli/plot_signature_matrix.py
gopca/cli/print_info.py
gopca-0.2.5.dist-info/DESCRIPTION.rst
gopca-0.2.5.dist-info/METADATA
gopca-0.2.5.dist-info/RECORD
gopca-0.2.5.dist-info/WHEEL
gopca-0.2.5.dist-info/entry_points.txt
gopca-0.2.5.dist-info/metadata.json
gopca-0.2.5.dist-info/top_level.txt
