Metadata-Version: 2.0
Name: gopca
Version: 0.2.5
Summary: GO-PCA: An Unsupervised Method to Explore Gene Expression Data Using Prior Knowledge
Home-page: https://github.com/flo-compbio/gopca
Author: Florian Wagner
Author-email: florian.wagner@duke.edu
License: GPLv3
Keywords: unsupervised analysis gene expression data transcriptomics prior knowledge
Platform: UNKNOWN
Classifier: Development Status :: 3 - Alpha
Classifier: Intended Audience :: Developers
Classifier: Intended Audience :: Science/Research
Classifier: Topic :: Scientific/Engineering :: Bio-Informatics
Classifier: License :: OSI Approved :: GNU General Public License v3 (GPLv3)
Classifier: Programming Language :: Python :: 2.7
Classifier: Programming Language :: Python :: 3.5
Requires-Dist: configparser (>=3.2,<4)
Requires-Dist: future (<1,>=0.16)
Requires-Dist: genometools (>=0.3,<0.4)
Requires-Dist: numpy (>=1.8,<2)
Requires-Dist: pandas (>=0.18,<1)
Requires-Dist: plotly (>=1.9.6,<3)
Requires-Dist: scikit-learn (>=0.14,<1)
Requires-Dist: scipy (>=0.14,<1)
Requires-Dist: setuptools (>=27.2.0)
Requires-Dist: six (>=1.5.2,<2)
Requires-Dist: unicodecsv (>=0.14.1,<1)
Requires-Dist: xlsxwriter (>=0.7.7,<1)
Provides-Extra: docs
Requires-Dist: mock; extra == 'docs'
Requires-Dist: sphinx; extra == 'docs'
Requires-Dist: sphinx-argparse; extra == 'docs'
Requires-Dist: sphinx-bootstrap-theme; extra == 'docs'
Provides-Extra: tests
Requires-Dist: pytest (<4,>=2.9.1); extra == 'tests'
Requires-Dist: pytest-cov (>=2.2.1,<3); extra == 'tests'
Requires-Dist: requests (<3,>=2.10.0); extra == 'tests'
